tokenize_rt.py
tokenize_rt-6.0.0.dist-info/LICENSE
tokenize_rt-6.0.0.dist-info/METADATA
tokenize_rt-6.0.0.dist-info/WHEEL
tokenize_rt-6.0.0.dist-info/entry_points.txt
tokenize_rt-6.0.0.dist-info/top_level.txt
tokenize_rt-6.0.0.dist-info/RECORD
