Metadata-Version: 2.1
Name: tokenize_rt
Version: 6.0.0
Summary: A wrapper around the stdlib `tokenize` which roundtrips.
Home-page: https://github.com/asottile/tokenize-rt
Author: Anthony Sottile
Author-email: asottile@umich.edu
License: MIT
Classifier: License :: OSI Approved :: MIT License
Classifier: Programming Language :: Python :: 3
Classifier: Programming Language :: Python :: 3 :: Only
Classifier: Programming Language :: Python :: Implementation :: CPython
Classifier: Programming Language :: Python :: Implementation :: PyPy
Requires-Python: >=3.8
License-File: LICENSE
